cua_mcp_server-0.1.16.dist-info/METADATA
cua_mcp_server-0.1.16.dist-info/WHEEL
cua_mcp_server-0.1.16.dist-info/entry_points.txt
mcp_server/__init__.py
mcp_server/__main__.py
mcp_server/server.py
mcp_server/session_manager.py
cua_mcp_server-0.1.16.dist-info/RECORD
