Metadata-Version: 2.1
Name: cua-mcp-server
Version: 0.1.16
Summary: MCP Server for Computer-Use Agent (Cua)
Author-Email: TryCua <gh@trycua.com>
Requires-Python: <3.14,>=3.12
Requires-Dist: mcp<2.0.0,>=1.6.0
Requires-Dist: cua-agent[all]<0.5.0,>=0.4.0
Requires-Dist: cua-computer<0.5.0,>=0.4.0
